pytest_polymeric_report/__init__.py
pytest_polymeric_report/pytest_custom_report.py
pytest_polymeric_report/templates/__init__.py
pytest_polymeric_report/templates/test_report_template.html
pytest_polymeric_report-0.1.8.dist-info/METADATA
pytest_polymeric_report-0.1.8.dist-info/WHEEL
pytest_polymeric_report-0.1.8.dist-info/entry_points.txt
pytest_polymeric_report-0.1.8.dist-info/top_level.txt
pytest_polymeric_report-0.1.8.dist-info/RECORD
