Metadata-Version: 2.4
Name: pytest-polymeric-report
Version: 0.1.8
Summary: A polymeric test report plugin for pytest
Author-email: "baojun.wang" <rimuli_w@163.com>
Classifier: Framework :: Pytest
Classifier: Programming Language :: Python :: 3
Classifier: License :: OSI Approved :: MIT License
Classifier: Operating System :: OS Independent
Requires-Python: >=3.7
